hammer.py
hammerlib.py
setup.py
hammerd.egg-info/PKG-INFO
hammerd.egg-info/SOURCES.txt
hammerd.egg-info/dependency_links.txt
hammerd.egg-info/entry_points.txt
hammerd.egg-info/requires.txt
hammerd.egg-info/top_level.txt