Metadata-Version: 1.0
Name: hammerd
Version: 0.1.1
Summary: HammerD Service and Helper libs
Home-page: http://www.hammerd.org/
Author: Amit Upadhyay
Author-email: upadhyay@gmail.com
License: BSD
Platform: UNKNOWN
